cli/__init__.py
cli/__main__.py
cli/database.py
cli/handlers.py
cli/main.py
cli/models.py
cli/sfmc.py
sfmcli-0.1.0.dist-info/METADATA
sfmcli-0.1.0.dist-info/WHEEL
sfmcli-0.1.0.dist-info/RECORD
