Metadata-Version: 2.1
Name: sfmcli
Version: 0.1.0
Summary: Saleforce marketing cloud data extension data migration made easy.
Author: Natan Siqueira Alves
Author-email: natan.siqueira@outlook.com.br
Requires-Python: >=3.11,<4.0
Classifier: Programming Language :: Python :: 3
Classifier: Programming Language :: Python :: 3.11
Requires-Dist: requests (>=2.31.0,<3.0.0)
Requires-Dist: sqlalchemy (>=2.0.17,<3.0.0)
Requires-Dist: tabulate (>=0.9.0,<0.10.0)
